pfehler/README.MD
pfehler/__init__.py
pfehler/requirements.txt
pfehler/thirdparty.json
pfehler-0.10.dist-info/LICENSE.rst
pfehler-0.10.dist-info/METADATA
pfehler-0.10.dist-info/WHEEL
pfehler-0.10.dist-info/top_level.txt
pfehler-0.10.dist-info/RECORD
