Metadata-Version: 2.1
Name: pfehler
Version: 0.10
Summary: Captures and logs exceptions, optionally printing them to stderr
Home-page: https://github.com/hansalemaos/pfehler
Author: Johannes Fischer
Author-email: aulasparticularesdealemaosp@gmail.com
License: MIT
Keywords: log,exceptions
Classifier: Development Status :: 4 - Beta
Classifier: Programming Language :: Python :: 3 :: Only
Classifier: Programming Language :: Python :: 3.10
Classifier: Topic :: Software Development :: Libraries :: Python Modules
Classifier: Topic :: Utilities
License-File: LICENSE.rst
Requires-Dist: stderrstdoutcapture
Requires-Dist: touchtouch
